gen3cirrus/__init__.py
gen3cirrus/aws/__init__.py
gen3cirrus/aws/services.py
gen3cirrus/aws/utils.py
gen3cirrus/backoff.py
gen3cirrus/config.py
gen3cirrus/core.py
gen3cirrus/errors.py
gen3cirrus/google_cloud/__init__.py
gen3cirrus/google_cloud/errors.py
gen3cirrus/google_cloud/iam.py
gen3cirrus/google_cloud/manager.py
gen3cirrus/google_cloud/services.py
gen3cirrus/google_cloud/utils.py
gen3cirrus-4.0.0.dist-info/METADATA
gen3cirrus-4.0.0.dist-info/WHEEL
gen3cirrus-4.0.0.dist-info/licenses/LICENSE
gen3cirrus-4.0.0.dist-info/licenses/NOTICE
gen3cirrus-4.0.0.dist-info/RECORD
