Metadata-Version: 2.4
Name: gen3cirrus
Version: 4.0.0
Summary: 
License: Apache-2.0
License-File: LICENSE
License-File: NOTICE
Author: Center for Translational Data Science at the University of Chicago
Author-email: support@gen3.org
Requires-Python: >=3.13,<4.0
Classifier: License :: OSI Approved :: Apache Software License
Classifier: Programming Language :: Python :: 3
Classifier: Programming Language :: Python :: 3.13
Classifier: Programming Language :: Python :: 3.14
Requires-Dist: backoff
Requires-Dist: boto3
Requires-Dist: botocore
Requires-Dist: cdislogging
Requires-Dist: google-api-python-client
Requires-Dist: google-auth
Requires-Dist: google-cloud-storage
Requires-Dist: httplib2
Requires-Dist: oauth2client
Requires-Dist: requests
